{
	"configurations" : 
	[
		{
			"directories" : 
			[
				{
					"build" : ".",
					"jsonFile" : "directory-.-Debug-d0094a50bb2071803777.json",
					"minimumCMakeVersion" : 
					{
						"string" : "3.21"
					},
					"projectIndex" : 0,
					"source" : ".",
					"targetIndexes" : 
					[
						0
					]
				}
			],
			"name" : "Debug",
			"projects" : 
			[
				{
					"directoryIndexes" : 
					[
						0
					],
					"name" : "CH13TEMPLATESP22",
					"targetIndexes" : 
					[
						0
					]
				}
			],
			"targets" : 
			[
				{
					"directoryIndex" : 0,
					"id" : "CH13TEMPLATESP22::@6890427a1f51a3e7e1df",
					"jsonFile" : "target-CH13TEMPLATESP22-Debug-d0f6ef12a0b3fc8e3b7e.json",
					"name" : "CH13TEMPLATESP22",
					"projectIndex" : 0
				}
			]
		}
	],
	"kind" : "codemodel",
	"paths" : 
	{
		"build" : "C:/Users/hloi/CLionProjects/CSC109/CH13TEMPLATESP22/cmake-build-debug",
		"source" : "C:/Users/hloi/CLionProjects/CSC109/CH13TEMPLATESP22"
	},
	"version" : 
	{
		"major" : 2,
		"minor" : 3
	}
}
